sopel_election
